open_plus/__init__.py
open_plus-0.2.dist-info/METADATA
open_plus-0.2.dist-info/WHEEL
open_plus-0.2.dist-info/top_level.txt
open_plus-0.2.dist-info/RECORD
