Metadata-Version: 2.1
Name: open-plus
Version: 0.2
Summary: 一个更好用的open()|An easier open()
Home-page: https://libraries.io/pypi/open-plus
Author: CharlesCai
Author-email: 18222159844@163.com
Maintainer: 蔡沐含
Maintainer-email: c6661366613@qq.com
License: GPL License
Platform: all
Classifier: Development Status :: 4 - Beta
Classifier: Operating System :: OS Independent
Classifier: Intended Audience :: Developers
Classifier: Programming Language :: Python
Classifier: Programming Language :: Python :: Implementation
Classifier: Programming Language :: Python :: 3
Classifier: Topic :: Software Development :: Libraries
Requires-Python: >=2.7
